pyquilted/__init__.py
pyquilted/app_factory.py
pyquilted/cli_main.py
pyquilted/html_app.py
pyquilted/main.py
pyquilted/pdf_app.py
pyquilted/pdf_printer.py
pyquilted/resume_builder.py
pyquilted/resume_to_html.py
pyquilted/sample_app.py
pyquilted/template_render.py
pyquilted/yaml_loader.py
pyquilted/builder/__init__.py
pyquilted/builder/contacts.py
pyquilted/builder/details.py
pyquilted/builder/education.py
pyquilted/builder/group.py
pyquilted/builder/heading.py
pyquilted/builder/projects.py
pyquilted/builder/resume.py
pyquilted/builder/section_factory.py
pyquilted/builder/skills.py
pyquilted/builder/work.py
pyquilted/mapper/__init__.py
pyquilted/mapper/contacts.py
pyquilted/mapper/details.py
pyquilted/mapper/education.py
pyquilted/mapper/heading.py
pyquilted/mapper/heading_details.py
pyquilted/mapper/projects.py
pyquilted/mapper/section.py
pyquilted/mapper/skills.py
pyquilted/mapper/work.py
pyquilted/quilted/__init__.py
pyquilted/quilted/contact.py
pyquilted/quilted/contact_factory.py
pyquilted/quilted/contacts.py
pyquilted/quilted/contacts_list.py
pyquilted/quilted/detail.py
pyquilted/quilted/detail_factory.py
pyquilted/quilted/education.py
pyquilted/quilted/group.py
pyquilted/quilted/heading.py
pyquilted/quilted/heading_complex.py
pyquilted/quilted/heading_details.py
pyquilted/quilted/heading_simple.py
pyquilted/quilted/iconify.py
pyquilted/quilted/projects.py
pyquilted/quilted/resume.py
pyquilted/quilted/section.py
pyquilted/quilted/skills.py
pyquilted/quilted/skills_table.py
pyquilted/quilted/style.py
pyquilted/quilted/style_options.py
pyquilted/quilted/table.py
pyquilted/quilted/work.py
pyquilted/sample/resume.yml
pyquilted/templates/base.mustache
pyquilted/templates/contacts.mustache
pyquilted/templates/education.mustache
pyquilted/templates/group.mustache
pyquilted/templates/grouping.mustache
pyquilted/templates/heading-simple.mustache
pyquilted/templates/heading.mustache
pyquilted/templates/projects.mustache
pyquilted/templates/skills-table.mustache
pyquilted-0.7.4.dist-info/LICENSE
pyquilted-0.7.4.dist-info/METADATA
pyquilted-0.7.4.dist-info/WHEEL
pyquilted-0.7.4.dist-info/entry_points.txt
pyquilted-0.7.4.dist-info/top_level.txt
pyquilted-0.7.4.dist-info/RECORD
