Metadata-Version: 2.1
Name: pyquilted
Version: 0.7.4
Summary: convert a yaml file to a pdf resume
Home-page: https://github.com/cocoroutine/pyquilted
Author: Hong Tuyen
Author-email: hong@coroutine.co
License: MIT
Keywords: quilted resume
Platform: UNKNOWN
Classifier: Development Status :: 4 - Beta
Classifier: License :: OSI Approved :: MIT License
Classifier: Programming Language :: Python :: 3.5
Classifier: Programming Language :: Python :: 3.6
Classifier: Programming Language :: Python :: 3.7
Requires-Dist: pystache
Requires-Dist: pdfkit
Requires-Dist: ruamel.yaml
